setup.py
tc_buildchain_stats/__init__.py
tc_buildchain_stats/gatherer.py
tc_buildchain_stats.egg-info/PKG-INFO
tc_buildchain_stats.egg-info/SOURCES.txt
tc_buildchain_stats.egg-info/dependency_links.txt
tc_buildchain_stats.egg-info/entry_points.txt
tc_buildchain_stats.egg-info/pbr.json
tc_buildchain_stats.egg-info/requires.txt
tc_buildchain_stats.egg-info/top_level.txt