Metadata-Version: 1.1
Name: tc-buildchain-stats
Version: 0.4
Summary: Gather stats of TeamCity build chains
Home-page: https://github.com/noroute/teamcity-buildchain-stats
Author: Florian Thiel
Author-email: github@noroute.de
License: MIT License
Keywords: teamcity process metrics stats buildchain
Platform: UNKNOWN
Classifier: Development Status :: 3 - Alpha
Classifier: Intended Audience :: Developers
Classifier: License :: OSI Approved :: MIT License
Classifier: Programming Language :: Python :: 2
Classifier: Programming Language :: Python :: 2.7
